memo/__init__.py
memo/__main__.py
memo/algorithms.py
memo/argparser.py
memo/awesome.py
memo/files.py
memo/ioutil.py
memo/myhash.py
memo/paths.py
memo/subcommands.py
memo/util.py
meow_memo-0.0.10.dist-info/METADATA
meow_memo-0.0.10.dist-info/WHEEL
meow_memo-0.0.10.dist-info/entry_points.txt
meow_memo-0.0.10.dist-info/top_level.txt
meow_memo-0.0.10.dist-info/RECORD
