Metadata-Version: 2.1
Name: meow-memo
Version: 0.0.10
Summary: Quick memo
Home-page: UNKNOWN
Author: TkskKurumi
Maintainer: TkskKurumi
Maintainer-email: zafkielkurumi@gmail.com
License: UNKNOWN
Platform: UNKNOWN
Requires-Dist: colorama
